{"premiership": {"Exeter Chiefs": {"Total For": "83", "Home For": "50", "Away For": "33", "First Half For": "42", "Second Half For": "41", "0-20 For": "18", "21-40 For": "24", "41-60 For": "25", "61-80 For": "17", "Matches Played For": "22", "Total Against": "56", "Home Against": "20", "Away Against": "36", "First Half Against": "23", "Second Half Against": "33", "0-20 Against": "11", "21-40 Against": "12", "41-60 Against": "13", "61-80 Against": "21", "Matches Played Against": "22"}, "London Wasps": {"Total For": "81", "Home For": "54", "Away For": "27", "First Half For": "32", "Second Half For": "49", "0-20 For": "14", "21-40 For": "18", "41-60 For": "21", "61-80 For": "28", "Matches Played For": "22", "Total Against": "58", "Home Against": "29", "Away Against": "29", "First Half Against": "26", "Second Half Against": "32", "0-20 Against": "12", "21-40 Against": "15", "41-60 Against": "19", "61-80 Against": "14", "Matches Played Against": "22"}, "Gloucester": {"Total For": "72", "Home For": "40", "Away For": "32", "First Half For": "28", "Second Half For": "44", "0-20 For": "12", "21-40 For": "16", "41-60 For": "20", "61-80 For": "24", "Matches Played For": "22", "Total Against": "55", "Home Against": "20", "Away Against": "35", "First Half Against": "26", "Second Half Against": "29", "0-20 Against": "12", "21-40 Against": "14", "41-60 Against": "20", "61-80 Against": "11", "Matches Played Against": "22"}, "Saracens": {"Total For": "71", "Home For": "45", "Away For": "26", "First Half For": "32", "Second Half For": "39", "0-20 For": "15", "21-40 For": "17", "41-60 For": "21", "61-80 For": "18", "Matches Played For": "22", "Total Against": "55", "Home Against": "22", "Away Against": "33", "First Half Against": "29", "Second Half Against": "26", "0-20 Against": "18", "21-40 Against": "13", "41-60 Against": "12", "61-80 Against": "14", "Matches Played Against": "22"}, "Bristol Bears": {"Total For": "70", "Home For": "38", "Away For": "32", "First Half For": "26", "Second Half For": "44", "0-20 For": "16", "21-40 For": "10", "41-60 For": "15", "61-80 For": "30", "Matches Played For": "22", "Total Against": "53", "Home Against": "17", "Away Against": "36", "First Half Against": "25", "Second Half Against": "28", "0-20 Against": "14", "21-40 Against": "11", "41-60 Against": "11", "61-80 Against": "17", "Matches Played Against": "22"}, "Sale Sharks": {"Total For": "69", "Home For": "37", "Away For": "32", "First Half For": "37", "Second Half For": "32", "0-20 For": "19", "21-40 For": "18", "41-60 For": "13", "61-80 For": "20", "Matches Played For": "21", "Total Against": "37", "Home Against": "16", "Away Against": "21", "First Half Against": "11", "Second Half Against": "26", "0-20 Against": "6", "21-40 Against": "5", "41-60 Against": "15", "61-80 Against": "11", "Matches Played Against": "21"}, "Harlequins": {"Total For": "63", "Home For": "31", "Away For": "32", "First Half For": "26", "Second Half For": "37", "0-20 For": "13", "21-40 For": "13", "41-60 For": "22", "61-80 For": "18", "Matches Played For": "22", "Total Against": "63", "Home Against": "28", "Away Against": "35", "First Half Against": "35", "Second Half Against": "28", "0-20 Against": "21", "21-40 Against": "14", "41-60 Against": "12", "61-80 Against": "18", "Matches Played Against": "22"}, "Bath": {"Total For": "59", "Home For": "27", "Away For": "32", "First Half For": "28", "Second Half For": "31", "0-20 For": "16", "21-40 For": "12", "41-60 For": "16", "61-80 For": "16", "Matches Played For": "22", "Total Against": "56", "Home Against": "21", "Away Against": "35", "First Half Against": "23", "Second Half Against": "33", "0-20 Against": "15", "21-40 Against": "8", "41-60 Against": "14", "61-80 Against": "20", "Matches Played Against": "22"}, "Northampton Saints": {"Total For": "52", "Home For": "29", "Away For": "23", "First Half For": "27", "Second Half For": "25", "0-20 For": "9", "21-40 For": "18", "41-60 For": "13", "61-80 For": "13", "Matches Played For": "22", "Total Against": "69", "Home Against": "33", "Away Against": "36", "First Half Against": "30", "Second Half Against": "39", "0-20 Against": "20", "21-40 Against": "12", "41-60 Against": "19", "61-80 Against": "21", "Matches Played Against": "22"}, "London Irish": {"Total For": "50", "Home For": "28", "Away For": "22", "First Half For": "22", "Second Half For": "28", "0-20 For": "13", "21-40 For": "9", "41-60 For": "12", "61-80 For": "18", "Matches Played For": "22", "Total Against": "88", "Home Against": "54", "Away Against": "34", "First Half Against": "37", "Second Half Against": "51", "0-20 Against": "16", "21-40 Against": "24", "41-60 Against": "21", "61-80 Against": "30", "Matches Played Against": "22"}, "Worcester Warriors": {"Total For": "42", "Home For": "26", "Away For": "16", "First Half For": "23", "Second Half For": "19", "0-20 For": "14", "21-40 For": "9", "41-60 For": "8", "61-80 For": "11", "Matches Played For": "21", "Total Against": "78", "Home Against": "31", "Away Against": "47", "First Half Against": "34", "Second Half Against": "44", "0-20 Against": "17", "21-40 Against": "18", "41-60 Against": "19", "61-80 Against": "26", "Matches Played Against": "21"}, "Leicester Tigers": {"Total For": "35", "Home For": "22", "Away For": "13", "First Half For": "15", "Second Half For": "20", "0-20 For": "9", "21-40 For": "6", "41-60 For": "11", "61-80 For": "10", "Matches Played For": "22", "Total Against": "79", "Home Against": "29", "Away Against": "50", "First Half Against": "39", "Second Half Against": "40", "0-20 Against": "16", "21-40 Against": "24", "41-60 Against": "22", "61-80 Against": "20", "Matches Played Against": "22"}}, "championship": {"Newcastle Falcons": {"Total For": "72", "Home For": "45", "Away For": "27", "First Half For": "38", "Second Half For": "34", "0-20 For": "16", "21-40 For": "22", "41-60 For": "18", "61-80 For": "17", "Matches Played For": "15", "Total Against": "18", "Home Against": "12", "Away Against": "6", "First Half Against": "4", "Second Half Against": "14", "0-20 Against": "0", "21-40 Against": "4", "41-60 Against": "4", "61-80 Against": "10", "Matches Played Against": "15"}, "Ealing Trailfinders": {"Total For": "66", "Home For": "38", "Away For": "28", "First Half For": "28", "Second Half For": "38", "0-20 For": "16", "21-40 For": "12", "41-60 For": "19", "61-80 For": "20", "Matches Played For": "14", "Total Against": "35", "Home Against": "20", "Away Against": "15", "First Half Against": "13", "Second Half Against": "22", "0-20 Against": "9", "21-40 Against": "4", "41-60 Against": "7", "61-80 Against": "15", "Matches Played Against": "14"}, "Coventry": {"Total For": "54", "Home For": "26", "Away For": "28", "First Half For": "23", "Second Half For": "31", "0-20 For": "12", "21-40 For": "11", "41-60 For": "11", "61-80 For": "21", "Matches Played For": "15", "Total Against": "38", "Home Against": "12", "Away Against": "26", "First Half Against": "21", "Second Half Against": "17", "0-20 Against": "10", "21-40 Against": "11", "41-60 Against": "11", "61-80 Against": "7", "Matches Played Against": "15"}, "Jersey": {"Total For": "47", "Home For": "24", "Away For": "23", "First Half For": "19", "Second Half For": "28", "0-20 For": "14", "21-40 For": "5", "41-60 For": "13", "61-80 For": "16", "Matches Played For": "14", "Total Against": "41", "Home Against": "13", "Away Against": "28", "First Half Against": "20", "Second Half Against": "21", "0-20 Against": "6", "21-40 Against": "14", "41-60 Against": "10", "61-80 Against": "11", "Matches Played Against": "14"}, "Cornish Pirates": {"Total For": "46", "Home For": "28", "Away For": "18", "First Half For": "24", "Second Half For": "22", "0-20 For": "12", "21-40 For": "12", "41-60 For": "12", "61-80 For": "10", "Matches Played For": "15", "Total Against": "27", "Home Against": "9", "Away Against": "18", "First Half Against": "14", "Second Half Against": "13", "0-20 Against": "10", "21-40 Against": "4", "41-60 Against": "5", "61-80 Against": "9", "Matches Played Against": "15"}, "Ampthill": {"Total For": "44", "Home For": "23", "Away For": "21", "First Half For": "17", "Second Half For": "27", "0-20 For": "7", "21-40 For": "10", "41-60 For": "12", "61-80 For": "16", "Matches Played For": "15", "Total Against": "55", "Home Against": "28", "Away Against": "27", "First Half Against": "30", "Second Half Against": "25", "0-20 Against": "13", "21-40 Against": "18", "41-60 Against": "13", "61-80 Against": "14", "Matches Played Against": "15"}, "London Scottish": {"Total For": "42", "Home For": "18", "Away For": "24", "First Half For": "22", "Second Half For": "20", "0-20 For": "11", "21-40 For": "11", "41-60 For": "7", "61-80 For": "13", "Matches Played For": "14", "Total Against": "37", "Home Against": "16", "Away Against": "21", "First Half Against": "17", "Second Half Against": "20", "0-20 Against": "10", "21-40 Against": "9", "41-60 Against": "9", "61-80 Against": "12", "Matches Played Against": "14"}, "Nottingham": {"Total For": "39", "Home For": "15", "Away For": "24", "First Half For": "17", "Second Half For": "22", "0-20 For": "9", "21-40 For": "8", "41-60 For": "10", "61-80 For": "13", "Matches Played For": "14", "Total Against": "31", "Home Against": "15", "Away Against": "16", "First Half Against": "16", "Second Half Against": "15", "0-20 Against": "6", "21-40 Against": "10", "41-60 Against": "6", "61-80 Against": "10", "Matches Played Against": "14"}, "Bedford Blues": {"Total For": "35", "Home For": "16", "Away For": "19", "First Half For": "23", "Second Half For": "12", "0-20 For": "11", "21-40 For": "12", "41-60 For": "8", "61-80 For": "5", "Matches Played For": "15", "Total Against": "41", "Home Against": "13", "Away Against": "28", "First Half Against": "22", "Second Half Against": "19", "0-20 Against": "15", "21-40 Against": "8", "41-60 Against": "12", "61-80 Against": "7", "Matches Played Against": "15"}, "Doncaster Knights": {"Total For": "30", "Home For": "15", "Away For": "15", "First Half For": "15", "Second Half For": "15", "0-20 For": "6", "21-40 For": "9", "41-60 For": "6", "61-80 For": "9", "Matches Played For": "15", "Total Against": "50", "Home Against": "21", "Away Against": "29", "First Half Against": "26", "Second Half Against": "24", "0-20 Against": "16", "21-40 Against": "11", "41-60 Against": "12", "61-80 Against": "13", "Matches Played Against": "15"}, "Hartpury College": {"Total For": "27", "Home For": "18", "Away For": "9", "First Half For": "14", "Second Half For": "13", "0-20 For": "5", "21-40 For": "9", "41-60 For": "6", "61-80 For": "8", "Matches Played For": "14", "Total Against": "42", "Home Against": "17", "Away Against": "25", "First Half Against": "21", "Second Half Against": "21", "0-20 Against": "11", "21-40 Against": "10", "41-60 Against": "6", "61-80 Against": "15", "Matches Played Against": "14"}, "Yorkshire Carnegie": {"Total For": "24", "Home For": "17", "Away For": "7", "First Half For": "11", "Second Half For": "13", "0-20 For": "5", "21-40 For": "6", "41-60 For": "3", "61-80 For": "10", "Matches Played For": "14", "Total Against": "111", "Home Against": "67", "Away Against": "44", "First Half Against": "47", "Second Half Against": "64", "0-20 Against": "23", "21-40 Against": "24", "41-60 Against": "30", "61-80 Against": "35", "Matches Played Against": "14"}}}
